<?xml version="1.0" encoding="UTF-8" standalone="no"?>
<worldnodes>
    <node>
        <type>ObstacleSignifier</type>
        <name>totem_obstacle</name>
        <uniqueID>138811</uniqueID>
        <xPosition>90.500000</xPosition>
        <yPosition>566.326294</yPosition>
        <zPosition>100.000000</zPosition>
        <motionType>0</motionType>
        <speedType>0</speedType>
    </node>
    <node>
        <type>ObstacleSignifier</type>
        <name>totem_obstacle</name>
        <uniqueID>795703</uniqueID>
        <xPosition>701.192322</xPosition>
        <yPosition>249.643799</yPosition>
        <zPosition>100.000000</zPosition>
        <motionType>0</motionType>
        <speedType>0</speedType>
    </node>
    <node>
        <type>ObstacleSignifier</type>
        <name>totem2_obstacle</name>
        <uniqueID>573485</uniqueID>
        <xPosition>701.192322</xPosition>
        <yPosition>1089.171387</yPosition>
        <zPosition>100.000000</zPosition>
        <motionType>0</motionType>
        <speedType>0</speedType>
    </node>
    <node>
        <type>ObstacleSignifier</type>
        <name>totem_obstacle</name>
        <uniqueID>555260</uniqueID>
        <xPosition>1329.149780</xPosition>
        <yPosition>543.171387</yPosition>
        <zPosition>100.000000</zPosition>
        <motionType>0</motionType>
        <speedType>0</speedType>
    </node>
</worldnodes>