<?xml version="1.0" encoding="UTF-8" standalone="no"?>
<worldnodes>
    <node>
        <type>ObstacleSignifier</type>
        <name>obstacle4_obstacle</name>
        <uniqueID>361533</uniqueID>
        <xPosition>137.500000</xPosition>
        <yPosition>1075.997925</yPosition>
        <zPosition>100.000000</zPosition>
        <motionType>0</motionType>
        <speedType>0</speedType>
    </node>
    <node>
        <type>ObstacleSignifier</type>
        <name>batmaskmaskbat_obstacle</name>
        <uniqueID>889441</uniqueID>
        <xPosition>180.355957</xPosition>
        <yPosition>523.940552</yPosition>
        <zPosition>100.000000</zPosition>
        <motionType>4</motionType>
        <speedType>0</speedType>
    </node>
    <node>
        <type>ObstacleSignifier</type>
        <name>rosemary_obstacle</name>
        <uniqueID>894030</uniqueID>
        <xPosition>587.937866</xPosition>
        <yPosition>520.057617</yPosition>
        <zPosition>100.000000</zPosition>
        <motionType>0</motionType>
        <speedType>0</speedType>
    </node>
    <node>
        <type>ObstacleSignifier</type>
        <name>batmaskmaskbat_obstacle</name>
        <uniqueID>568749</uniqueID>
        <xPosition>592.542358</xPosition>
        <yPosition>181.161652</yPosition>
        <zPosition>100.000000</zPosition>
        <motionType>4</motionType>
        <speedType>0</speedType>
    </node>
    <node>
        <type>ObstacleSignifier</type>
        <name>batmaskmaskbat_obstacle</name>
        <uniqueID>394578</uniqueID>
        <xPosition>592.885132</xPosition>
        <yPosition>872.879211</yPosition>
        <zPosition>100.000000</zPosition>
        <motionType>3</motionType>
        <speedType>0</speedType>
    </node>
    <node>
        <type>ObstacleSignifier</type>
        <name>rosemary_obstacle</name>
        <uniqueID>197442</uniqueID>
        <xPosition>600.088257</xPosition>
        <yPosition>15.005768</yPosition>
        <zPosition>100.000000</zPosition>
        <motionType>0</motionType>
        <speedType>0</speedType>
    </node>
    <node>
        <type>ObstacleSignifier</type>
        <name>batmaskmaskbat_obstacle</name>
        <uniqueID>157296</uniqueID>
        <xPosition>991.785278</xPosition>
        <yPosition>554.488037</yPosition>
        <zPosition>100.000000</zPosition>
        <motionType>3</motionType>
        <speedType>0</speedType>
    </node>
    <node>
        <type>ObstacleSignifier</type>
        <name>obstacle4_obstacle</name>
        <uniqueID>367564</uniqueID>
        <xPosition>1179.284424</xPosition>
        <yPosition>1064.788818</yPosition>
        <zPosition>100.000000</zPosition>
        <motionType>0</motionType>
        <speedType>0</speedType>
    </node>
    <node>
        <type>ObstacleSignifier</type>
        <name>obstacle4_obstacle</name>
        <uniqueID>123852</uniqueID>
        <xPosition>1677.573730</xPosition>
        <yPosition>38.646584</yPosition>
        <zPosition>100.000000</zPosition>
        <motionType>0</motionType>
        <speedType>0</speedType>
    </node>
    <node>
        <type>ObstacleSignifier</type>
        <name>rosemary_obstacle</name>
        <uniqueID>356444</uniqueID>
        <xPosition>1832.596680</xPosition>
        <yPosition>893.706421</yPosition>
        <zPosition>100.000000</zPosition>
        <motionType>0</motionType>
        <speedType>0</speedType>
    </node>
    <node>
        <type>ObstacleSignifier</type>
        <name>rosemary_obstacle</name>
        <uniqueID>815183</uniqueID>
        <xPosition>1973.521240</xPosition>
        <yPosition>966.787598</yPosition>
        <zPosition>100.000000</zPosition>
        <motionType>0</motionType>
        <speedType>0</speedType>
    </node>
    <node>
        <type>ObstacleSignifier</type>
        <name>rosemary_obstacle</name>
        <uniqueID>408416</uniqueID>
        <xPosition>2137.078125</xPosition>
        <yPosition>559.889526</yPosition>
        <zPosition>100.000000</zPosition>
        <motionType>1</motionType>
        <speedType>2</speedType>
    </node>
    <node>
        <type>ObstacleSignifier</type>
        <name>rosemary_obstacle</name>
        <uniqueID>430583</uniqueID>
        <xPosition>2324.173340</xPosition>
        <yPosition>965.037964</yPosition>
        <zPosition>100.000000</zPosition>
        <motionType>0</motionType>
        <speedType>0</speedType>
    </node>
    <node>
        <type>ObstacleSignifier</type>
        <name>rosemary_obstacle</name>
        <uniqueID>397012</uniqueID>
        <xPosition>2461.076660</xPosition>
        <yPosition>872.684814</yPosition>
        <zPosition>100.000000</zPosition>
        <motionType>0</motionType>
        <speedType>0</speedType>
    </node>
    <node>
        <type>ObstacleSignifier</type>
        <name>obstacle4_obstacle</name>
        <uniqueID>991575</uniqueID>
        <xPosition>2606.386230</xPosition>
        <yPosition>38.646576</yPosition>
        <zPosition>100.000000</zPosition>
        <motionType>0</motionType>
        <speedType>0</speedType>
    </node>
</worldnodes>